localprojections/__init__.py
localprojections/__main__.py
localprojections/lp.py
localprojections-0.2.1.dist-info/LICENSE
localprojections-0.2.1.dist-info/METADATA
localprojections-0.2.1.dist-info/WHEEL
localprojections-0.2.1.dist-info/entry_points.txt
localprojections-0.2.1.dist-info/top_level.txt
localprojections-0.2.1.dist-info/RECORD
