Metadata-Version: 2.1
Name: localprojections
Version: 0.2.1
Summary: This module implements the local projections models for single entity time series and panel / longitudinal data, as well as threshold versions.
Author-email: Jing Lian Suah <jlsuah@hkma.gov.hk>
License: MIT License
Project-URL: PyPI, https://pypi.org/project/localprojections/
Project-URL: GitHub, https://github.com/suahjl/localprojections/
Keywords: Econometrics,Local Projections,Panel Data,Time Series
Classifier: License :: OSI Approved :: MIT License
Classifier: Programming Language :: Python
Classifier: Programming Language :: Python :: 3
Requires-Python: >=3.9
License-File: LICENSE
Requires-Dist: pandas>=1.4.3
Requires-Dist: numpy>=1.23.0
Requires-Dist: linearmodels>=4.27
Requires-Dist: plotly>=5.9.0
Requires-Dist: statsmodels>=0.13.2
Provides-Extra: dev
